stackler/dev.py
stackler/display_utils.py
stackler/git_utils.py
stackler/main.py
stackler/phab_utils.py
stackler/shell.py
stackler/shell_runner.py
stackler-0.2.2.dist-info/entry_points.txt
stackler-0.2.2.dist-info/WHEEL
stackler-0.2.2.dist-info/METADATA
stackler-0.2.2.dist-info/RECORD
