Metadata-Version: 2.1
Name: stackler
Version: 0.2.2
Summary: 
Author: Modun
Author-email: modun@xiaohongshu.com
Requires-Python: >=3.7.2,<4.0.0
Classifier: Programming Language :: Python :: 3
Classifier: Programming Language :: Python :: 3.10
Classifier: Programming Language :: Python :: 3.8
Classifier: Programming Language :: Python :: 3.9
Requires-Dist: GitPython (==3.1.27)
Requires-Dist: ansiwrap (>=0.8.4,<0.9.0)
Requires-Dist: click (==8.1.3)
Requires-Dist: humanize (>=4.3.0,<5.0.0)
Requires-Dist: phabricator (==0.9.1)
Requires-Dist: pyperclip (>=1.8.2,<2.0.0)
Requires-Dist: termcolor (==1.1.0)
Requires-Dist: typer (==0.6.1)
Requires-Dist: wcwidth (>=0.2.5,<0.3.0)
